{
	"parent": "minecraft:block/block",
	"display": {
        "gui": {
            "rotation": [ 30, 225, 0 ],
            "translation": [ 0, -1, 0],
            "scale":[ 0.5, 0.5, 0.5 ]
        },
        "firstperson_righthand": {
            "rotation": [ 0, 135, 0 ],
            "translation": [ 0, 0, 0 ],
            "scale": [ 0.4, 0.4, 0.4 ]
        }
	},
	"texture_size": [32, 32],
	"textures": {
		"4": "seven-elements:block/infusion_table_base_top",
		"5": "minecraft:block/smooth_stone",
		"6": "seven-elements:block/infusion_table_stem",
		"7": "seven-elements:block/infusion_table_top",
		"particle": "seven-elements:block/infusion_table_base_top"
	},
	"elements": [
		{
			"from": [3, 0, 3],
			"to": [13, 2, 13],
			"rotation": {"angle": 0, "axis": "y", "origin": [2, 16, 0]},
			"faces": {
				"north": {"uv": [3, 3, 4, 13], "rotation": 270, "texture": "#4"},
				"east": {"uv": [3, 3, 13, 4], "rotation": 180, "texture": "#4"},
				"south": {"uv": [12, 3, 13, 13], "rotation": 90, "texture": "#4"},
				"west": {"uv": [3, 12, 13, 13], "texture": "#4"},
				"up": {"uv": [3, 3, 13, 13], "rotation": 90, "texture": "#4"},
				"down": {"uv": [3, 3, 13, 13], "rotation": 270, "texture": "#4"}
			}
		},
		{
			"from": [11, 0, 3],
			"to": [12, 2, 4],
			"rotation": {"angle": 0, "axis": "y", "origin": [10, 16, 3]},
			"faces": {
				"north": {"uv": [3, 4, 3.5, 5], "texture": "#4"},
				"east": {"uv": [3, 4, 3.5, 5], "texture": "#4"},
				"south": {"uv": [3, 4, 3.5, 5], "texture": "#4"},
				"west": {"uv": [3, 4, 3.5, 5], "texture": "#4"},
				"up": {"uv": [3, 4, 3.5, 4.5], "texture": "#4"},
				"down": {"uv": [3, 4, 3.5, 4.5], "texture": "#4"}
			}
		},
		{
			"from": [12, 0, 4],
			"to": [13, 2, 5],
			"rotation": {"angle": 0, "axis": "y", "origin": [11, 16, 4]},
			"faces": {
				"north": {"uv": [4, 3, 4.5, 4], "texture": "#4"},
				"east": {"uv": [4, 3, 4.5, 4], "texture": "#4"},
				"south": {"uv": [4, 3, 4.5, 4], "texture": "#4"},
				"west": {"uv": [4, 3, 4.5, 4], "texture": "#4"},
				"up": {"uv": [4, 3, 4.5, 3.5], "texture": "#4"},
				"down": {"uv": [4, 3, 4.5, 3.5], "texture": "#4"}
			}
		},
		{
			"from": [4, 0, 3],
			"to": [5, 2, 4],
			"rotation": {"angle": 0, "axis": "y", "origin": [3, 16, 2]},
			"faces": {
				"north": {"uv": [3, 11, 3.5, 12], "texture": "#4"},
				"east": {"uv": [3, 11, 3.5, 12], "texture": "#4"},
				"south": {"uv": [3, 11, 3.5, 12], "texture": "#4"},
				"west": {"uv": [3, 11, 3.5, 12], "texture": "#4"},
				"up": {"uv": [3, 11, 3.5, 11.5], "texture": "#4"},
				"down": {"uv": [3, 11, 3.5, 11.5], "texture": "#4"}
			}
		},
		{
			"from": [3, 0, 4],
			"to": [4, 2, 5],
			"rotation": {"angle": 0, "axis": "y", "origin": [2, 16, 3]},
			"faces": {
				"north": {"uv": [4, 12, 4.5, 13], "texture": "#4"},
				"east": {"uv": [4, 12, 4.5, 13], "texture": "#4"},
				"south": {"uv": [4, 12, 4.5, 13], "texture": "#4"},
				"west": {"uv": [4, 12, 4.5, 13], "texture": "#4"},
				"up": {"uv": [4, 12, 4.5, 12.5], "texture": "#4"},
				"down": {"uv": [4, 12, 4.5, 12.5], "texture": "#4"}
			}
		},
		{
			"from": [3, 0, 11],
			"to": [4, 2, 12],
			"rotation": {"angle": 0, "axis": "y", "origin": [2, 16, 10]},
			"faces": {
				"north": {"uv": [11, 12, 11.5, 13], "texture": "#4"},
				"east": {"uv": [11, 12, 11.5, 13], "texture": "#4"},
				"south": {"uv": [11, 12, 11.5, 13], "texture": "#4"},
				"west": {"uv": [11, 12, 11.5, 13], "texture": "#4"},
				"up": {"uv": [11, 12, 11.5, 12.5], "texture": "#4"},
				"down": {"uv": [11, 12, 11.5, 12.5], "texture": "#4"}
			}
		},
		{
			"from": [4, 0, 12],
			"to": [5, 2, 13],
			"rotation": {"angle": 0, "axis": "y", "origin": [3, 16, 11]},
			"faces": {
				"north": {"uv": [12, 11, 12.5, 12], "texture": "#4"},
				"east": {"uv": [12, 11, 12.5, 12], "texture": "#4"},
				"south": {"uv": [12, 11, 12.5, 12], "texture": "#4"},
				"west": {"uv": [12, 11, 12.5, 12], "texture": "#4"},
				"up": {"uv": [12, 11, 12.5, 11.5], "texture": "#4"},
				"down": {"uv": [12, 11, 12.5, 11.5], "texture": "#4"}
			}
		},
		{
			"from": [11, 0, 12],
			"to": [12, 2, 13],
			"rotation": {"angle": 0, "axis": "y", "origin": [10, 16, 11]},
			"faces": {
				"north": {"uv": [12, 4, 12.5, 5], "texture": "#4"},
				"east": {"uv": [12, 4, 12.5, 5], "texture": "#4"},
				"south": {"uv": [12, 4, 12.5, 5], "texture": "#4"},
				"west": {"uv": [12, 4, 12.5, 5], "texture": "#4"},
				"up": {"uv": [12, 4, 12.5, 4.5], "texture": "#4"},
				"down": {"uv": [12, 4, 12.5, 4.5], "texture": "#4"}
			}
		},
		{
			"from": [0, 2, 0],
			"to": [16, 4, 16],
			"rotation": {"angle": 0, "axis": "y", "origin": [16, 18, 2]},
			"faces": {
				"north": {"uv": [0, 0, 16, 1], "rotation": 180, "texture": "#7"},
				"east": {"uv": [15, 0, 16, 16], "rotation": 90, "texture": "#7"},
				"south": {"uv": [0, 15, 16, 16], "texture": "#7"},
				"west": {"uv": [0, 0, 1, 16], "rotation": 270, "texture": "#7"},
				"up": {"uv": [16, 16, 0, 0], "rotation": 180, "texture": "#7"},
				"down": {"uv": [16, 0, 0, 16], "rotation": 180, "texture": "#7"}
			}
		},
		{
			"from": [0, 2, 0],
			"to": [16, 4, 16],
			"rotation": {"angle": 0, "axis": "y", "origin": [16, 18, 2]},
			"faces": {
				"north": {"uv": [0, 0, 16, 1], "rotation": 180, "texture": "#7"},
				"east": {"uv": [15, 0, 16, 16], "rotation": 90, "texture": "#7"},
				"south": {"uv": [0, 15, 16, 16], "texture": "#7"},
				"west": {"uv": [0, 0, 1, 16], "rotation": 270, "texture": "#7"},
				"up": {"uv": [16, 16, 0, 0], "rotation": 180, "texture": "#7"},
				"down": {"uv": [16, 0, 0, 16], "rotation": 180, "texture": "#7"}
			}
		}
	],
	"groups": [
		{
			"name": "top",
			"origin": [8, 8, 8],
			"color": 0,
			"children": [
				{
					"name": "textured_top",
					"origin": [2, 16, 0],
					"color": 0,
					"children": [0, 1, 2, 3, 4, 5, 6, 7, 8]
				},
				9
			]
		}
	]
}